owen/__init__.py
owen/excel/__init__.py
owen/excel/test.py
owen/mysql/__init__.py
owen/mysql/diymysql.py
owen-0.1.dist-info/METADATA
owen-0.1.dist-info/WHEEL
owen-0.1.dist-info/top_level.txt
owen-0.1.dist-info/RECORD
