Metadata-Version: 2.1
Name: owen
Version: 0.1
Summary: owen
Author: owen
Author-email: 758024724@qq.com
Requires-Python: >=3.7
